seleniumer/__init__.py
seleniumer/seleniumer.py
seleniumer/test_seleniumer.py
seleniumer-1.0.3.dist-info/METADATA
seleniumer-1.0.3.dist-info/WHEEL
seleniumer-1.0.3.dist-info/top_level.txt
seleniumer-1.0.3.dist-info/RECORD
